README.md
setup.cfg
setup.py
brain_plasma/__init__.py
brain_plasma/brain.py
brain_plasma/brain_client.py
brain_plasma/compatibility.py
brain_plasma/exceptions.py
brain_plasma/mock.py
brain_plasma.egg-info/PKG-INFO
brain_plasma.egg-info/SOURCES.txt
brain_plasma.egg-info/dependency_links.txt
brain_plasma.egg-info/not-zip-safe
brain_plasma.egg-info/requires.txt
brain_plasma.egg-info/top_level.txt
tests/__init__.py
tests/test_brain.py